clone_page/__init__.py
clone_page/clone_page.py
clone_page-0.0.7.dist-info/METADATA
clone_page-0.0.7.dist-info/WHEEL
clone_page-0.0.7.dist-info/entry_points.txt
clone_page-0.0.7.dist-info/top_level.txt
clone_page-0.0.7.dist-info/RECORD
