Metadata-Version: 2.1
Name: clone-page
Version: 0.0.7
Summary: A script for downloading complete web pages with assets
Author: jaytrairat
Author-email: jaytrairat@outlook.com
Requires-Dist: beautifulsoup4
Requires-Dist: requests
Requires-Dist: tqdm
